azure/maps/route/__init__.py
azure/maps/route/_client.py
azure/maps/route/_configuration.py
azure/maps/route/_patch.py
azure/maps/route/_serialization.py
azure/maps/route/_version.py
azure/maps/route/py.typed
azure/maps/route/aio/__init__.py
azure/maps/route/aio/_client.py
azure/maps/route/aio/_configuration.py
azure/maps/route/aio/_patch.py
azure/maps/route/aio/operations/__init__.py
azure/maps/route/aio/operations/_operations.py
azure/maps/route/aio/operations/_patch.py
azure/maps/route/models/__init__.py
azure/maps/route/models/_enums.py
azure/maps/route/models/_models.py
azure/maps/route/models/_patch.py
azure/maps/route/operations/__init__.py
azure/maps/route/operations/_operations.py
azure/maps/route/operations/_patch.py
azure_maps_route-1.0.0b3.dist-info/METADATA
azure_maps_route-1.0.0b3.dist-info/WHEEL
azure_maps_route-1.0.0b3.dist-info/top_level.txt
azure_maps_route-1.0.0b3.dist-info/RECORD
